dankware/__init__.py
dankware/ctypes.py
dankware/datetime.py
dankware/multithread.py
dankware/pillow.py
dankware/requests.py
dankware/terminal.py
dankware/text.py
dankware/tkinter.py
dankware/traceback.py
dankware/winreg.py
dankware-3.6.10.dist-info/licenses/LICENSE
dankware-3.6.10.dist-info/METADATA
dankware-3.6.10.dist-info/WHEEL
dankware-3.6.10.dist-info/top_level.txt
dankware-3.6.10.dist-info/RECORD
