Metadata-Version: 2.4
Name: dankware
Version: 3.6.10
Summary: Python package with various features!
Home-page: https://github.com/SirDank/dankware
Author: SirDank
Author-email: SirDankenstein@protonmail.com
License: MIT
Project-URL: GitHub, https://github.com/SirDank/dankware
Project-URL: Bug Tracker, https://github.com/SirDank/dankware/issues
Keywords: dank,dankware,multithread,gradient,fade,registry key,error traceback,random ip,github scraper,splash screen,windows tools,terminal
Classifier: Programming Language :: Python
Classifier: Programming Language :: Python :: 3
Classifier: License :: OSI Approved :: GNU General Public License v3 or later (GPLv3+)
Classifier: Operating System :: Microsoft :: Windows
Classifier: Operating System :: POSIX :: Linux
Classifier: Development Status :: 5 - Production/Stable
Classifier: Intended Audience :: Developers
Classifier: Natural Language :: English
Classifier: Topic :: Software Development
License-File: LICENSE
Requires-Dist: rich
Requires-Dist: colorama
Requires-Dist: requests
Provides-Extra: extras
Requires-Dist: pillow; extra == "extras"
Dynamic: author
Dynamic: author-email
Dynamic: classifier
Dynamic: description
Dynamic: description-content-type
Dynamic: home-page
Dynamic: keywords
Dynamic: license
Dynamic: license-file
Dynamic: project-url
Dynamic: provides-extra
Dynamic: requires-dist
Dynamic: summary
